libx/__init__.py
libx/env/__init__.py
libx/log/__init__.py
libx/owl/__init__.py
libx/owl/interface.py
libx/sty/__init__.py
libx/til/__init__.py
libx/til/faker.py
libx-1.2.5.dist-info/WHEEL
libx-1.2.5.dist-info/METADATA
libx-1.2.5.dist-info/RECORD
