Metadata-Version: 2.1
Name: libx
Version: 1.2.5
Summary: alleviates anxiety.
Home-page: http://github.com/lmist/libx
License: UNLICENSED
Keywords: pretty,logging,dotenvies,mailer,templates,webscraping
Author: lmisto
Author-email: louaimisto@gmail.com
Requires-Python: >=3.10,<4.0
Classifier: Development Status :: 5 - Production/Stable
Classifier: Environment :: Web Environment
Classifier: Framework :: Pytest
Classifier: Intended Audience :: Developers
Classifier: License :: OSI Approved :: MIT License
Classifier: License :: Other/Proprietary License
Classifier: Operating System :: MacOS :: MacOS X
Classifier: Operating System :: POSIX
Classifier: Programming Language :: Python
Classifier: Programming Language :: Python :: 3
Classifier: Programming Language :: Python :: 3.10
Classifier: Programming Language :: Python :: 3.10
Classifier: Programming Language :: Python :: 3.7
Classifier: Programming Language :: Python :: 3.8
Classifier: Programming Language :: Python :: 3.9
Classifier: Programming Language :: Python :: Implementation :: PyPy
Classifier: Topic :: Software Development :: Libraries :: Python Modules
Classifier: Topic :: System :: Shells
Classifier: Topic :: Utilities
Classifier: Typing :: Typed
Provides-Extra: coverage
Provides-Extra: docs
Provides-Extra: format
Provides-Extra: lint
Provides-Extra: test
Requires-Dist: beautifulsoup4 (>=4.11.1,<5.0.0)
Requires-Dist: chalky (>=1.0.0,<2.0.0)
Requires-Dist: fontawesome (>=5.10.1.post1,<6.0.0)
Requires-Dist: lxml (>=4.9.1,<5.0.0)
Requires-Dist: pandas (>=1.4.4,<2.0.0)
Requires-Dist: ptpython (>=3.0.20,<4.0.0)
Requires-Dist: pydantic (>=1.10.2,<2.0.0)
Requires-Dist: python-dotenv (>=0.21.0,<0.22.0)
Requires-Dist: randomname (>=0.1.5,<0.2.0)
Requires-Dist: requests (>=2.28.1,<3.0.0)
Requires-Dist: typer (>=0.6.1,<0.7.0)
Project-URL: Bug Tracker, https://github.com/lmist/libx/issues
Project-URL: Changes, https://github.com/lmist/libx/blob/master/CHANGES
Project-URL: Documentation, https://libx.git-pull.com
Project-URL: Repository, https://github.com/lmist/libx
